pyllmlink/__init__.py
pyllmlink/cli.py
pyllmlink-0.3.9.dist-info/METADATA
pyllmlink-0.3.9.dist-info/WHEEL
pyllmlink-0.3.9.dist-info/entry_points.txt
pyllmlink-0.3.9.dist-info/top_level.txt
pyllmlink-0.3.9.dist-info/RECORD
