Metadata-Version: 2.4
Name: pyllmlink
Version: 0.3.9
Summary: Python wrapper that downloads and launches the llm-link binary
Author: LLM Link Maintainers
License: MIT
Project-URL: Homepage, https://github.com/lipish/llm-link
Project-URL: Repository, https://github.com/lipish/llm-link
Project-URL: Issues, https://github.com/lipish/llm-link/issues
Keywords: llm,proxy,cli
Classifier: Programming Language :: Python
Classifier: Programming Language :: Python :: 3
Classifier: Programming Language :: Python :: 3 :: Only
Classifier: License :: OSI Approved :: MIT License
Classifier: Operating System :: MacOS
Classifier: Operating System :: POSIX :: Linux
Classifier: Topic :: Software Development :: Libraries
Requires-Python: >=3.8
